sw_mc_lib/Component.py
sw_mc_lib/Input.py
sw_mc_lib/Microcontroller.py
sw_mc_lib/Node.py
sw_mc_lib/NumberProperty.py
sw_mc_lib/Position.py
sw_mc_lib/Types.py
sw_mc_lib/XMLElement.py
sw_mc_lib/XMLFormatter.py
sw_mc_lib/XMLParser.py
sw_mc_lib/__init__.py
sw_mc_lib/_resources.py
sw_mc_lib/helper.py
sw_mc_lib/layout.py
sw_mc_lib/optimizer.py
sw_mc_lib/py.typed
sw_mc_lib/util.py
sw_mc_lib/Components/__init__.py
sw_mc_lib/Components/abs.py
sw_mc_lib/Components/add.py
sw_mc_lib/Components/and_.py
sw_mc_lib/Components/arithmetic_function_1_in.py
sw_mc_lib/Components/arithmetic_function_3_in.py
sw_mc_lib/Components/arithmetic_function_8_in.py
sw_mc_lib/Components/audio_switchbox.py
sw_mc_lib/Components/blinker.py
sw_mc_lib/Components/boolean_function_4_in.py
sw_mc_lib/Components/boolean_function_8_in.py
sw_mc_lib/Components/capacitor.py
sw_mc_lib/Components/clamp.py
sw_mc_lib/Components/composite_binary_to_number.py
sw_mc_lib/Components/composite_read_boolean.py
sw_mc_lib/Components/composite_read_number.py
sw_mc_lib/Components/composite_switchbox.py
sw_mc_lib/Components/composite_write_boolean.py
sw_mc_lib/Components/composite_write_number.py
sw_mc_lib/Components/constant_number.py
sw_mc_lib/Components/constant_on.py
sw_mc_lib/Components/delta.py
sw_mc_lib/Components/divide.py
sw_mc_lib/Components/equal.py
sw_mc_lib/Components/greater_than.py
sw_mc_lib/Components/jk_flip_flop.py
sw_mc_lib/Components/less_than.py
sw_mc_lib/Components/lua_script.py
sw_mc_lib/Components/memory_register.py
sw_mc_lib/Components/modulo.py
sw_mc_lib/Components/multiply.py
sw_mc_lib/Components/nand.py
sw_mc_lib/Components/nor.py
sw_mc_lib/Components/not_.py
sw_mc_lib/Components/number_to_composite_binary.py
sw_mc_lib/Components/numerical_junction.py
sw_mc_lib/Components/numerical_switchbox.py
sw_mc_lib/Components/or_.py
sw_mc_lib/Components/pid_controller.py
sw_mc_lib/Components/pid_controller_advanced.py
sw_mc_lib/Components/property_dropdown.py
sw_mc_lib/Components/property_number.py
sw_mc_lib-0.4.13.dist-info/licenses/LICENSE
sw_mc_lib-0.4.13.dist-info/METADATA
sw_mc_lib-0.4.13.dist-info/WHEEL
sw_mc_lib-0.4.13.dist-info/top_level.txt
sw_mc_lib-0.4.13.dist-info/RECORD
