Metadata-Version: 2.4
Name: sw_mc_lib
Version: 0.4.13
Summary: Library for interaction with Stormworks Microcontrollers
Author: Fabian Wunsch
License-Expression: MIT
Project-URL: homepage, https://github.com/stormworks-utils/sw_mc_lib
Project-URL: repository, https://github.com/stormworks-utils/sw_mc_lib
Keywords: stormworks,lib,microcontroller
Classifier: Programming Language :: Python :: 3
Classifier: Development Status :: 3 - Alpha
Classifier: Intended Audience :: Developers
Classifier: Intended Audience :: Information Technology
Classifier: Natural Language :: English
Classifier: Operating System :: OS Independent
Classifier: Topic :: Games/Entertainment :: Simulation
Classifier: Topic :: Software Development :: Libraries
Classifier: Typing :: Typed
Requires-Python: >=3.10
License-File: LICENSE
Requires-Dist: pillow>=11.0.0
Provides-Extra: dev
Requires-Dist: black; extra == "dev"
Requires-Dist: isort; extra == "dev"
Requires-Dist: pip-tools; extra == "dev"
Requires-Dist: mypy; extra == "dev"
Requires-Dist: flake8; extra == "dev"
Requires-Dist: coverage; extra == "dev"
Requires-Dist: pylint; extra == "dev"
Dynamic: license-file
